lsld2/__init__.py
lsld2/cli.py
lsld2/command_line.py
lsld2-0.0.6.dist-info/LICENSE
lsld2-0.0.6.dist-info/METADATA
lsld2-0.0.6.dist-info/WHEEL
lsld2-0.0.6.dist-info/top_level.txt
lsld2-0.0.6.dist-info/RECORD
