Metadata-Version: 2.1
Name: lsld2
Version: 0.0.6
Summary: TODO
Home-page: https://github.com/Xiaoy01/lsld2
Author: Sean Yang, Pranav Gupta
Author-email: acert@cornell.edu
License: MIT
Platform: UNKNOWN
Classifier: Development Status :: 2 - Pre-Alpha
Classifier: Programming Language :: Python :: 3.6
Classifier: Topic :: Scientific/Engineering :: Chemistry
License-File: LICENSE
Requires-Dist: markdown
